.gitignore
LICENSE
MANIFEST.in
README.rst
mglex-cli
setup.py
MGLEX.egg-info/PKG-INFO
MGLEX.egg-info/SOURCES.txt
MGLEX.egg-info/dependency_links.txt
MGLEX.egg-info/requires.txt
MGLEX.egg-info/top_level.txt
doc/Makefile
doc/make.bat
doc/source/conf.py
doc/source/data.rst
doc/source/help.rst
doc/source/index.rst
doc/source/install.rst
doc/source/quickstart.rst
mglex/__init__.py
mglex/common.py
mglex/evaluation.py
mglex/types.py
mglex/cli/__init__.py
mglex/cli/bincompare.py
mglex/cli/buildmatrix.py
mglex/cli/classify.py
mglex/cli/evaluate.py
mglex/cli/significance.py
mglex/cli/spread.py
mglex/cli/train.py
mglex/cli/transform.py
mglex/models/__init__.py
mglex/models/aggregate.py
mglex/models/hierarchic_naive_bayes.py
mglex/models/multinomial.py
mglex/models/naive_bayes.py
mglex/models/poisson.py