Metadata-Version: 1.1
Name: MGLEX
Version: 0.2.1
Summary: MGLEX - MetaGenome Likelihood EXtractor
Home-page: https://github.com/fungs/mglex
Author: Johannes Dröge
Author-email: code@fungs.de
License: GNU General Public License, version 3 (GPL-3.0)
Platform: UNKNOWN
Classifier: Development Status :: 4 - Beta
Classifier: Topic :: Scientific/Engineering :: Bio-Informatics
Classifier: License :: OSI Approved :: GNU General Public License v3 (GPLv3)
Classifier: Programming Language :: Python
Classifier: Programming Language :: Python :: 3
Classifier: Programming Language :: Python :: 3 :: Only
Classifier: Programming Language :: Python :: 3.4
Classifier: Programming Language :: Python :: 3.5
Classifier: Operating System :: POSIX :: Linux
